pynosql_logger/__init__.py
pynosql_logger/async_loggers.py
pynosql_logger/classes.py
pynosql_logger/constant.py
pynosql_logger/helper.py
pynosql_logger/loggers.py
pynosql_logger/tests.py
python_nosql_logger-1.1.6.dist-info/LICENSE
python_nosql_logger-1.1.6.dist-info/METADATA
python_nosql_logger-1.1.6.dist-info/WHEEL
python_nosql_logger-1.1.6.dist-info/top_level.txt
python_nosql_logger-1.1.6.dist-info/RECORD
