Metadata-Version: 2.1
Name: python-nosql-logger
Version: 1.1.6
Summary: For logging & accessing application data with NoSQL databases (MongoDB & ElasticSearch)
Home-page: https://github.com/hiteshmishra708/python-nosql-logger
Author: Hitesh Mishra
Author-email: hiteshmishra708@gmail.com
License: UNKNOWN
Project-URL: Bug Reports, https://github.com/hiteshmishra708/python-nosql-logger/issues
Project-URL: Say Thanks!, https://linkedin.com/in/hiteshmishra708/
Project-URL: Source, https://github.com/hiteshmishra708/python-nosql-logger/
Keywords: logger,django logger,flask logger,nosql logger,mongodb logger,setuptools,development,elasticsearch,elastic search logging
Platform: UNKNOWN
Classifier: Development Status :: 3 - Alpha
Classifier: Intended Audience :: Developers
Classifier: Topic :: Software Development :: Build Tools
Classifier: License :: OSI Approved :: MIT License
Classifier: Programming Language :: Python :: 3
Classifier: Programming Language :: Python :: 3.6
Classifier: Programming Language :: Python :: 3.7
Classifier: Programming Language :: Python :: 3.8
Classifier: Programming Language :: Python :: 3.9
Classifier: Programming Language :: Python :: 3.10
Classifier: Programming Language :: Python :: 3 :: Only
Requires-Python: >=3.6, <4
Requires-Dist: requests
